{
  "_fv": 47,
  "_type": "dimension",
  "definition": {
    "biomesInDimension": [
      {
        "value": "beaches"
      }
    ],
    "worldGenType": "End like gen",
    "mainFillerBlock": {
      "value": "Blocks.DIRT#0"
    },
    "fluidBlock": {
      "value": "Blocks.DIRT#0"
    },
    "airColor": {
      "value": -13369345,
      "falpha": 0.0
    },
    "canRespawnHere": true,
    "hasFog": false,
    "isDark": false,
    "doesWaterVaporize": false,
    "sleepResult": "ALLOW",
    "hasSkyLight": true,
    "imitateOverworldBehaviour": true,
    "portalFrame": {
      "value": "Blocks.VERDANT_FROGLIGHT"
    },
    "portalParticles": {
      "value": "PORTAL"
    },
    "portalLuminance": 0,
    "portalSound": {
      "value": "block.portal.ambient"
    },
    "enableIgniter": true,
    "igniterName": "Heathen Igniter",
    "specialInfo": [],
    "igniterTab": {
      "value": "TOOLS"
    },
    "texture": "heathen_igniter",
    "portalTexture": "m_cracked",
    "enablePortal": true
  }
}